[
  {
    "name": "about",
    "path": "/about",
    "component": "C:\\\\WebStormProjects\\\\NuxtSonDers\\\\7-middleware-cookies-localstorage-auth-baslangic-kodu\\\\pages\\\\about.vue",
    "chunkName": "pages/about",
    "_name": "_0ccc79dd"
  },
  {
    "name": "auth",
    "path": "/auth",
    "component": "C:\\\\WebStormProjects\\\\NuxtSonDers\\\\7-middleware-cookies-localstorage-auth-baslangic-kodu\\\\pages\\\\auth\\\\index.vue",
    "chunkName": "pages/auth/index",
    "_name": "_50598f0c"
  },
  {
    "name": "index",
    "path": "/",
    "component": "C:\\\\WebStormProjects\\\\NuxtSonDers\\\\7-middleware-cookies-localstorage-auth-baslangic-kodu\\\\pages\\\\index.vue",
    "chunkName": "pages/index",
    "_name": "_2c8454a2"
  }
]
